altmindpy/__init__.py
altmindpy/_base_client.py
altmindpy/_client.py
altmindpy/_compat.py
altmindpy/_constants.py
altmindpy/_exceptions.py
altmindpy/_files.py
altmindpy/_models.py
altmindpy/_qs.py
altmindpy/_resource.py
altmindpy/_response.py
altmindpy/_streaming.py
altmindpy/_types.py
altmindpy/_version.py
altmindpy/py.typed
altmindpy/_utils/__init__.py
altmindpy/_utils/_logs.py
altmindpy/_utils/_proxy.py
altmindpy/_utils/_reflection.py
altmindpy/_utils/_streams.py
altmindpy/_utils/_sync.py
altmindpy/_utils/_transform.py
altmindpy/_utils/_typing.py
altmindpy/_utils/_utils.py
altmindpy/lib/.keep
altmindpy/resources/__init__.py
altmindpy/resources/assistants.py
altmindpy/resources/experimental.py
altmindpy/resources/login.py
altmindpy/resources/runs.py
altmindpy/resources/threads.py
altmindpy/resources/users.py
altmindpy/resources/files/__init__.py
altmindpy/resources/files/content.py
altmindpy/resources/files/files.py
altmindpy/resources/messages/__init__.py
altmindpy/resources/messages/messages.py
altmindpy/resources/messages/thread.py
altmindpy/types/__init__.py
altmindpy/types/assistant_create_params.py
altmindpy/types/assistant_delete.py
altmindpy/types/assistant_list_params.py
altmindpy/types/assistant_response.py
altmindpy/types/assistant_update_params.py
altmindpy/types/assistants_response.py
altmindpy/types/experimental_stream_params.py
altmindpy/types/file_create_params.py
altmindpy/types/file_delete.py
altmindpy/types/file_list_params.py
altmindpy/types/file_response.py
altmindpy/types/files_response.py
altmindpy/types/login_access_token_params.py
altmindpy/types/message_create_params.py
altmindpy/types/message_delete.py
altmindpy/types/message_list_params.py
altmindpy/types/message_response.py
altmindpy/types/message_update_params.py
altmindpy/types/messages_response.py
altmindpy/types/response_message.py
altmindpy/types/run_create_params.py
altmindpy/types/run_list_params.py
altmindpy/types/run_response.py
altmindpy/types/run_update_params.py
altmindpy-0.5.0.dist-info/METADATA
altmindpy-0.5.0.dist-info/WHEEL
altmindpy-0.5.0.dist-info/licenses/LICENSE
altmindpy-0.5.0.dist-info/RECORD
